MANIFEST.in
README.txt
setup.py
collective/__init__.py
collective.monkeypatcherpanel.egg-info/PKG-INFO
collective.monkeypatcherpanel.egg-info/SOURCES.txt
collective.monkeypatcherpanel.egg-info/dependency_links.txt
collective.monkeypatcherpanel.egg-info/entry_points.txt
collective.monkeypatcherpanel.egg-info/namespace_packages.txt
collective.monkeypatcherpanel.egg-info/not-zip-safe
collective.monkeypatcherpanel.egg-info/requires.txt
collective.monkeypatcherpanel.egg-info/top_level.txt
collective/monkeypatcherpanel/__init__.py
collective/monkeypatcherpanel/config.py
collective/monkeypatcherpanel/configure.zcml
collective/monkeypatcherpanel/controlpanel.py
collective/monkeypatcherpanel/tests.py
collective/monkeypatcherpanel/utils.py
collective/monkeypatcherpanel/version.txt
collective/monkeypatcherpanel/zmi/controlpanel.pt
collective/monkeypatcherpanel/zmi/face-monkey.png
docs/HISTORY.txt
docs/INSTALL.txt