Metadata-Version: 1.1
Name: collective.monkeypatcherpanel
Version: 1.0.4
Summary: A Zope 2 control panel that shows monkey patches applied by collective.monkeypatcher
Home-page: http://pypi.python.org/pypi/collective.monkeypatcherpanel
Author: Gilles Lenfant
Author-email: gilles.lenfant@gmail.com
License: GPL
Keywords: zope monkey patch panel
Platform: UNKNOWN
Classifier: Framework :: Zope2
Classifier: Programming Language :: Python
Classifier: Topic :: Software Development :: Libraries :: Python Modules
